navas_etl/__init__.py
navas_etl/extractors/__init__.py
navas_etl/extractors/api_extractor.py
navas_etl/extractors/csv_extractor.py
navas_etl/extractors/db_extractor.py
navas_etl/loaders/__init__.py
navas_etl/loaders/csv_loader.py
navas_etl/loaders/db_loader.py
navas_etl/loaders/json_loader.py
navas_etl/transformers/__init__.py
navas_etl/transformers/aggregator.py
navas_etl/transformers/cleaner.py
navas_etl/transformers/formatter.py
navas_etl-0.1.1.dist-info/METADATA
navas_etl-0.1.1.dist-info/WHEEL
navas_etl-0.1.1.dist-info/top_level.txt
navas_etl-0.1.1.dist-info/RECORD
