Metadata-Version: 2.4
Name: navas-etl
Version: 0.1.1
Summary: A flexible ELT pipeline implementation in Python
Author-email: Navas_Herbert <navasmuller01@gmail.com>
Project-URL: Homepage, https://github.com/Navashub/navas_pipeline
Classifier: Programming Language :: Python :: 3
Classifier: License :: OSI Approved :: MIT License
Classifier: Operating System :: OS Independent
Requires-Python: >=3.8
Requires-Dist: pandas>=1.0
Requires-Dist: requests>=2.0
Requires-Dist: sqlalchemy>=1.4
